ludden_logging/__init__.py
ludden_logging/cwd.py
ludden_logging/log.py
ludden_logging/py.typed
ludden_logging/run.py
ludden_logging-0.1.8.dist-info/METADATA
ludden_logging-0.1.8.dist-info/WHEEL
ludden_logging-0.1.8.dist-info/RECORD
