Metadata-Version: 2.3
Name: ludden-logging
Version: 0.1.8
Summary: A project to automate logging in Python
Author-email: Max Ludden <dev@maxludden.com>
Requires-Python: >=3.10
Requires-Dist: loguru>=0.7.2
Requires-Dist: mypy>=1.12.1
Requires-Dist: python-dotenv[cli]>=1.0.1
Requires-Dist: rich-gradient>=0.1.7
Requires-Dist: rich>=13.8.0
Requires-Dist: sh>=2.0.7
